cuckoo/__init__.py
cuckoo/bucket.py
cuckoo/exception.py
cuckoo/filter.py
scalable_cuckoo_filter-1.1.dist-info/METADATA
scalable_cuckoo_filter-1.1.dist-info/RECORD
scalable_cuckoo_filter-1.1.dist-info/WHEEL
scalable_cuckoo_filter-1.1.dist-info/top_level.txt
