Metadata-Version: 2.1
Name: scalable-cuckoo-filter
Version: 1.1
Summary: Scalable Cuckoo filter
Home-page: https://github.com/huydhn/cuckoo-filter
Author: Huy Do
Author-email: huydhn@gmail.com
License: MIT
Platform: UNKNOWN
Classifier: Programming Language :: Python :: 3
Classifier: License :: OSI Approved :: MIT License
Classifier: Operating System :: OS Independent
